[
  {
    "Journal name": "ACCIDENT ANALYSIS AND PREVENTION",
    "ISSN": "0001-4575",
    "eISSN": "1879-2057",
    "Category": "ERGONOMICS",
    "Edition": "SSCI",
    "2025 JIF": 7.4,
    "5-year JIF": 8,
    "JIF quartile": "Q1",
    "JIF rank": "1/24"
  },
  {
    "Journal name": "INTERNATIONAL JOURNAL OF HUMAN-COMPUTER INTERACTION",
    "ISSN": "1044-7318",
    "eISSN": "1532-7590",
    "Category": "ERGONOMICS",
    "Edition": "SSCI",
    "2025 JIF": 6.1,
    "5-year JIF": 7,
    "JIF quartile": "Q1",
    "JIF rank": "2/24"
  },
  {
    "Journal name": "INTERNATIONAL JOURNAL OF HUMAN-COMPUTER STUDIES",
    "ISSN": "1071-5819",
    "eISSN": "1095-9300",
    "Category": "ERGONOMICS",
    "Edition": "SSCI",
    "2025 JIF": 6,
    "5-year JIF": 8.3,
    "JIF quartile": "Q1",
    "JIF rank": "3/24"
  },
  {
    "Journal name": "JOURNAL OF SAFETY RESEARCH",
    "ISSN": "0022-4375",
    "eISSN": "1879-1247",
    "Category": "ERGONOMICS",
    "Edition": "SSCI",
    "2025 JIF": 4.3,
    "5-year JIF": 4.8,
    "JIF quartile": "Q1",
    "JIF rank": "4/24"
  },
  {
    "Journal name": "BEHAVIOUR & INFORMATION TECHNOLOGY",
    "ISSN": "0144-929X",
    "eISSN": "1362-3001",
    "Category": "ERGONOMICS",
    "Edition": "SSCI",
    "2025 JIF": 4.2,
    "5-year JIF": 5,
    "JIF quartile": "Q1",
    "JIF rank": "5/24"
  },
  {
    "Journal name": "HUMAN FACTORS",
    "ISSN": "0018-7208",
    "eISSN": "1547-8181",
    "Category": "ERGONOMICS",
    "Edition": "SSCI",
    "2025 JIF": 3.6,
    "5-year JIF": 5.5,
    "JIF quartile": "Q1",
    "JIF rank": "6/24"
  },
  {
    "Journal name": "INTERNATIONAL JOURNAL OF INDUSTRIAL ERGONOMICS",
    "ISSN": "0169-8141",
    "eISSN": "1872-8219",
    "Category": "ERGONOMICS",
    "Edition": "SSCI",
    "2025 JIF": 3.6,
    "5-year JIF": 3.8,
    "JIF quartile": "Q1",
    "JIF rank": "6/24"
  },
  {
    "Journal name": "APPLIED ERGONOMICS",
    "ISSN": "0003-6870",
    "eISSN": "1872-9126",
    "Category": "ERGONOMICS",
    "Edition": "SSCI",
    "2025 JIF": 3.5,
    "5-year JIF": 4.2,
    "JIF quartile": "Q2",
    "JIF rank": "8/24"
  },
  {
    "Journal name": "Universal Access in the Information Society",
    "ISSN": "1615-5289",
    "eISSN": "1615-5297",
    "Category": "ERGONOMICS",
    "Edition": "SSCI",
    "2025 JIF": 3.1,
    "5-year JIF": 3.6,
    "JIF quartile": "Q2",
    "JIF rank": "9/24"
  },
  {
    "Journal name": "Frontiers in Neuroergonomics",
    "ISSN": "",
    "eISSN": "2673-6195",
    "Category": "ERGONOMICS",
    "Edition": "ESCI",
    "2025 JIF": 3.1,
    "5-year JIF": 3.2,
    "JIF quartile": "Q2",
    "JIF rank": "9/24"
  },
  {
    "Journal name": "Footwear Science",
    "ISSN": "1942-4280",
    "eISSN": "1942-4299",
    "Category": "ERGONOMICS",
    "Edition": "ESCI",
    "2025 JIF": 3,
    "5-year JIF": 3.1,
    "JIF quartile": "Q2",
    "JIF rank": "11/24"
  },
  {
    "Journal name": "ERGONOMICS",
    "ISSN": "0014-0139",
    "eISSN": "1366-5847",
    "Category": "ERGONOMICS",
    "Edition": "SSCI",
    "2025 JIF": 2.8,
    "5-year JIF": 3.1,
    "JIF quartile": "Q2",
    "JIF rank": "12/24"
  },
  {
    "Journal name": "Cognition Technology & Work",
    "ISSN": "1435-5558",
    "eISSN": "1435-5566",
    "Category": "ERGONOMICS",
    "Edition": "SSCI",
    "2025 JIF": 2.8,
    "5-year JIF": 3.5,
    "JIF quartile": "Q2",
    "JIF rank": "12/24"
  },
  {
    "Journal name": "Human Factors and Ergonomics in Manufacturing & Service Industries",
    "ISSN": "1090-8471",
    "eISSN": "1520-6564",
    "Category": "ERGONOMICS",
    "Edition": "SSCI",
    "2025 JIF": 2.4,
    "5-year JIF": 2.6,
    "JIF quartile": "Q3",
    "JIF rank": "14/24"
  },
  {
    "Journal name": "IISE Transactions on Occupational Ergonomics & Human Factors",
    "ISSN": "2472-5838",
    "eISSN": "2472-5846",
    "Category": "ERGONOMICS",
    "Edition": "ESCI",
    "2025 JIF": 1.9,
    "5-year JIF": 2.2,
    "JIF quartile": "Q3",
    "JIF rank": "15/24"
  },
  {
    "Journal name": "THEORETICAL ISSUES IN ERGONOMICS SCIENCE",
    "ISSN": "1463-922X",
    "eISSN": "1464-536X",
    "Category": "ERGONOMICS",
    "Edition": "ESCI",
    "2025 JIF": 1.9,
    "5-year JIF": 2.5,
    "JIF quartile": "Q3",
    "JIF rank": "15/24"
  },
  {
    "Journal name": "INTERACTING WITH COMPUTERS",
    "ISSN": "0953-5438",
    "eISSN": "1873-7951",
    "Category": "ERGONOMICS",
    "Edition": "SSCI",
    "2025 JIF": 1.9,
    "5-year JIF": 2.2,
    "JIF quartile": "Q3",
    "JIF rank": "15/24"
  },
  {
    "Journal name": "Journal of Cognitive Engineering and Decision Making",
    "ISSN": "1555-3434",
    "eISSN": "2169-5032",
    "Category": "ERGONOMICS",
    "Edition": "ESCI",
    "2025 JIF": 1.8,
    "5-year JIF": 3.3,
    "JIF quartile": "Q3",
    "JIF rank": "18/24"
  },
  {
    "Journal name": "International Journal of Occupational Safety and Ergonomics",
    "ISSN": "1080-3548",
    "eISSN": "2376-9130",
    "Category": "ERGONOMICS",
    "Edition": "SSCI",
    "2025 JIF": 1.8,
    "5-year JIF": 2.4,
    "JIF quartile": "Q3",
    "JIF rank": "18/24"
  },
  {
    "Journal name": "Human Factors in Healthcare",
    "ISSN": "",
    "eISSN": "2772-5014",
    "Category": "ERGONOMICS",
    "Edition": "ESCI",
    "2025 JIF": 1.6,
    "5-year JIF": 2.6,
    "JIF quartile": "Q4",
    "JIF rank": "20/24"
  },
  {
    "Journal name": "Ergonomics in Design",
    "ISSN": "1064-8046",
    "eISSN": "2169-5083",
    "Category": "ERGONOMICS",
    "Edition": "ESCI",
    "2025 JIF": 1.1,
    "5-year JIF": 1.3,
    "JIF quartile": "Q4",
    "JIF rank": "21/24"
  },
  {
    "Journal name": "International Journal of Human Factors and Ergonomics",
    "ISSN": "2045-7804",
    "eISSN": "2045-7812",
    "Category": "ERGONOMICS",
    "Edition": "ESCI",
    "2025 JIF": 0.5,
    "5-year JIF": "",
    "JIF quartile": "Q4",
    "JIF rank": "22/24"
  },
  {
    "Journal name": "TRAVAIL HUMAIN",
    "ISSN": "0041-1868",
    "eISSN": "2104-3663",
    "Category": "ERGONOMICS",
    "Edition": "SSCI",
    "2025 JIF": 0.4,
    "5-year JIF": 0.5,
    "JIF quartile": "Q4",
    "JIF rank": "23/24"
  },
  {
    "Journal name": "Activites-Revue Electronique",
    "ISSN": "1765-2723",
    "eISSN": "1765-2723",
    "Category": "ERGONOMICS",
    "Edition": "ESCI",
    "2025 JIF": 0.3,
    "5-year JIF": 0.4,
    "JIF quartile": "Q4",
    "JIF rank": "24/24"
  }
]