[
  {
    "Journal name": "MEDIA PSYCHOLOGY",
    "ISSN": "1521-3269",
    "eISSN": "1532-785X",
    "Category": "FILM, RADIO, TELEVISION",
    "Edition": "AHCI",
    "2025 JIF": 3,
    "5-year JIF": 4.9,
    "JIF quartile": "",
    "JIF rank": ""
  },
  {
    "Journal name": "POSITIF",
    "ISSN": "0048-4911",
    "eISSN": "",
    "Category": "FILM, RADIO, TELEVISION",
    "Edition": "AHCI",
    "2025 JIF": 3,
    "5-year JIF": 0.2,
    "JIF quartile": "",
    "JIF rank": ""
  },
  {
    "Journal name": "Television & New Media",
    "ISSN": "1527-4764",
    "eISSN": "1552-8316",
    "Category": "FILM, RADIO, TELEVISION",
    "Edition": "AHCI",
    "2025 JIF": 1.1,
    "5-year JIF": 2.6,
    "JIF quartile": "",
    "JIF rank": ""
  },
  {
    "Journal name": "Continuum-Journal of Media & Cultural Studies",
    "ISSN": "1030-4312",
    "eISSN": "1469-3666",
    "Category": "FILM, RADIO, TELEVISION",
    "Edition": "AHCI",
    "2025 JIF": 1,
    "5-year JIF": 1.1,
    "JIF quartile": "",
    "JIF rank": ""
  },
  {
    "Journal name": "Critical Studies in Television",
    "ISSN": "1749-6020",
    "eISSN": "1749-6039",
    "Category": "FILM, RADIO, TELEVISION",
    "Edition": "AHCI",
    "2025 JIF": 0.9,
    "5-year JIF": 1.5,
    "JIF quartile": "",
    "JIF rank": ""
  },
  {
    "Journal name": "Studies in Documentary Film",
    "ISSN": "1750-3280",
    "eISSN": "1750-3299",
    "Category": "FILM, RADIO, TELEVISION",
    "Edition": "ESCI",
    "2025 JIF": 0.6,
    "5-year JIF": 0.8,
    "JIF quartile": "",
    "JIF rank": ""
  },
  {
    "Journal name": "JCMS-Journal of Cinema and Media Studies",
    "ISSN": "2578-4900",
    "eISSN": "2578-4919",
    "Category": "FILM, RADIO, TELEVISION",
    "Edition": "AHCI",
    "2025 JIF": 0.6,
    "5-year JIF": 1,
    "JIF quartile": "",
    "JIF rank": ""
  },
  {
    "Journal name": "FILM QUARTERLY",
    "ISSN": "0015-1386",
    "eISSN": "1533-8630",
    "Category": "FILM, RADIO, TELEVISION",
    "Edition": "AHCI",
    "2025 JIF": 0.6,
    "5-year JIF": 1,
    "JIF quartile": "",
    "JIF rank": ""
  },
  {
    "Journal name": "Film-Philosophy",
    "ISSN": "1466-4615",
    "eISSN": "1466-4615",
    "Category": "FILM, RADIO, TELEVISION",
    "Edition": "AHCI",
    "2025 JIF": 0.6,
    "5-year JIF": 0.5,
    "JIF quartile": "",
    "JIF rank": ""
  },
  {
    "Journal name": "Animation-An Interdisciplinary Journal",
    "ISSN": "1746-8477",
    "eISSN": "1746-8485",
    "Category": "FILM, RADIO, TELEVISION",
    "Edition": "AHCI",
    "2025 JIF": 0.5,
    "5-year JIF": 0.8,
    "JIF quartile": "",
    "JIF rank": ""
  },
  {
    "Journal name": "Studies in Eastern European Cinema",
    "ISSN": "2040-350X",
    "eISSN": "2040-3518",
    "Category": "FILM, RADIO, TELEVISION",
    "Edition": "ESCI",
    "2025 JIF": 0.5,
    "5-year JIF": 0.7,
    "JIF quartile": "",
    "JIF rank": ""
  },
  {
    "Journal name": "SCREEN",
    "ISSN": "0036-9543",
    "eISSN": "1460-2474",
    "Category": "FILM, RADIO, TELEVISION",
    "Edition": "AHCI",
    "2025 JIF": 0.5,
    "5-year JIF": 0.5,
    "JIF quartile": "",
    "JIF rank": ""
  },
  {
    "Journal name": "Journal of Chinese Cinemas",
    "ISSN": "1750-8061",
    "eISSN": "1750-807X",
    "Category": "FILM, RADIO, TELEVISION",
    "Edition": "AHCI",
    "2025 JIF": 0.5,
    "5-year JIF": 0.7,
    "JIF quartile": "",
    "JIF rank": ""
  },
  {
    "Journal name": "Film History",
    "ISSN": "0892-2160",
    "eISSN": "1553-3905",
    "Category": "FILM, RADIO, TELEVISION",
    "Edition": "ESCI",
    "2025 JIF": 0.5,
    "5-year JIF": 0.4,
    "JIF quartile": "",
    "JIF rank": ""
  },
  {
    "Journal name": "Framework-The Journal of Cinema and Media",
    "ISSN": "0306-7661",
    "eISSN": "1559-7989",
    "Category": "FILM, RADIO, TELEVISION",
    "Edition": "ESCI",
    "2025 JIF": 0.5,
    "5-year JIF": 0.6,
    "JIF quartile": "",
    "JIF rank": ""
  },
  {
    "Journal name": "French Screen Studies",
    "ISSN": "2643-8941",
    "eISSN": "2643-895X",
    "Category": "FILM, RADIO, TELEVISION",
    "Edition": "AHCI",
    "2025 JIF": 0.4,
    "5-year JIF": 0.5,
    "JIF quartile": "",
    "JIF rank": ""
  },
  {
    "Journal name": "New Review of Film and Television Studies",
    "ISSN": "1740-0309",
    "eISSN": "1740-7923",
    "Category": "FILM, RADIO, TELEVISION",
    "Edition": "AHCI",
    "2025 JIF": 0.4,
    "5-year JIF": 0.4,
    "JIF quartile": "",
    "JIF rank": ""
  },
  {
    "Journal name": "Nauka Televideniya-The Art and Science of Television",
    "ISSN": "1994-9529",
    "eISSN": "2587-9782",
    "Category": "FILM, RADIO, TELEVISION",
    "Edition": "ESCI",
    "2025 JIF": 0.4,
    "5-year JIF": 0.2,
    "JIF quartile": "",
    "JIF rank": ""
  },
  {
    "Journal name": "Transnational Screens",
    "ISSN": "2578-5273",
    "eISSN": "2578-5265",
    "Category": "FILM, RADIO, TELEVISION",
    "Edition": "ESCI",
    "2025 JIF": 0.4,
    "5-year JIF": 0.5,
    "JIF quartile": "",
    "JIF rank": ""
  },
  {
    "Journal name": "Historia y Comunicacion Social",
    "ISSN": "1137-0734",
    "eISSN": "1988-3056",
    "Category": "FILM, RADIO, TELEVISION",
    "Edition": "AHCI",
    "2025 JIF": 0.4,
    "5-year JIF": 0.4,
    "JIF quartile": "",
    "JIF rank": ""
  },
  {
    "Journal name": "Bioscope-South Asian Screen Studies",
    "ISSN": "0974-9276",
    "eISSN": "0976-352X",
    "Category": "FILM, RADIO, TELEVISION",
    "Edition": "AHCI",
    "2025 JIF": 0.4,
    "5-year JIF": 0.5,
    "JIF quartile": "",
    "JIF rank": ""
  },
  {
    "Journal name": "Kino-The Western Undergraduate Journal of Film Studies",
    "ISSN": "1923-7561",
    "eISSN": "1923-7561",
    "Category": "FILM, RADIO, TELEVISION",
    "Edition": "ESCI",
    "2025 JIF": 0.4,
    "5-year JIF": 1.1,
    "JIF quartile": "",
    "JIF rank": ""
  },
  {
    "Journal name": "Studies in Australasian Cinema",
    "ISSN": "1750-3175",
    "eISSN": "1750-3183",
    "Category": "FILM, RADIO, TELEVISION",
    "Edition": "ESCI",
    "2025 JIF": 0.3,
    "5-year JIF": 0.4,
    "JIF quartile": "",
    "JIF rank": ""
  },
  {
    "Journal name": "Journal of Scandinavian Cinema",
    "ISSN": "2042-7891",
    "eISSN": "2042-7905",
    "Category": "FILM, RADIO, TELEVISION",
    "Edition": "ESCI",
    "2025 JIF": 0.3,
    "5-year JIF": 0.3,
    "JIF quartile": "",
    "JIF rank": ""
  },
  {
    "Journal name": "Journal of African Media Studies",
    "ISSN": "2040-199X",
    "eISSN": "1751-7974",
    "Category": "FILM, RADIO, TELEVISION",
    "Edition": "AHCI",
    "2025 JIF": 0.3,
    "5-year JIF": 0.6,
    "JIF quartile": "",
    "JIF rank": ""
  },
  {
    "Journal name": "HISTORICAL JOURNAL OF FILM RADIO AND TELEVISION",
    "ISSN": "0143-9685",
    "eISSN": "1465-3451",
    "Category": "FILM, RADIO, TELEVISION",
    "Edition": "AHCI",
    "2025 JIF": 0.3,
    "5-year JIF": 0.3,
    "JIF quartile": "",
    "JIF rank": ""
  },
  {
    "Journal name": "Fotocinema-Revista Cientifica de Cine y Fotografia",
    "ISSN": "2172-0150",
    "eISSN": "2172-0150",
    "Category": "FILM, RADIO, TELEVISION",
    "Edition": "ESCI",
    "2025 JIF": 0.3,
    "5-year JIF": 0.2,
    "JIF quartile": "",
    "JIF rank": ""
  },
  {
    "Journal name": "Journal of Popular Television",
    "ISSN": "2046-9861",
    "eISSN": "2046-987X",
    "Category": "FILM, RADIO, TELEVISION",
    "Edition": "ESCI",
    "2025 JIF": 0.2,
    "5-year JIF": 0.4,
    "JIF quartile": "",
    "JIF rank": ""
  },
  {
    "Journal name": "Journal of Screenwriting",
    "ISSN": "1759-7137",
    "eISSN": "1759-7145",
    "Category": "FILM, RADIO, TELEVISION",
    "Edition": "AHCI",
    "2025 JIF": 0.2,
    "5-year JIF": 0.2,
    "JIF quartile": "",
    "JIF rank": ""
  },
  {
    "Journal name": "Adaptation-The Journal of Literature on Screen Studies",
    "ISSN": "1755-0637",
    "eISSN": "1755-0645",
    "Category": "FILM, RADIO, TELEVISION",
    "Edition": "AHCI",
    "2025 JIF": 0.2,
    "5-year JIF": 0.5,
    "JIF quartile": "",
    "JIF rank": ""
  },
  {
    "Journal name": "JOURNAL OF POPULAR FILM AND TELEVISION",
    "ISSN": "0195-6051",
    "eISSN": "1930-6458",
    "Category": "FILM, RADIO, TELEVISION",
    "Edition": "AHCI",
    "2025 JIF": 0.2,
    "5-year JIF": 0.4,
    "JIF quartile": "",
    "JIF rank": ""
  },
  {
    "Journal name": "CINEJ Cinema Journal",
    "ISSN": "2159-2411",
    "eISSN": "2158-8724",
    "Category": "FILM, RADIO, TELEVISION",
    "Edition": "ESCI",
    "2025 JIF": 0.2,
    "5-year JIF": 0.3,
    "JIF quartile": "",
    "JIF rank": ""
  },
  {
    "Journal name": "Asian Cinema",
    "ISSN": "1059-440X",
    "eISSN": "2049-6710",
    "Category": "FILM, RADIO, TELEVISION",
    "Edition": "ESCI",
    "2025 JIF": 0.2,
    "5-year JIF": 0.6,
    "JIF quartile": "",
    "JIF rank": ""
  },
  {
    "Journal name": "Journal of British Cinema and Television",
    "ISSN": "1743-4521",
    "eISSN": "1755-1714",
    "Category": "FILM, RADIO, TELEVISION",
    "Edition": "AHCI",
    "2025 JIF": 0.2,
    "5-year JIF": 0.4,
    "JIF quartile": "",
    "JIF rank": ""
  },
  {
    "Journal name": "Studies in European Cinema",
    "ISSN": "1741-1548",
    "eISSN": "2040-0594",
    "Category": "FILM, RADIO, TELEVISION",
    "Edition": "ESCI",
    "2025 JIF": 0.2,
    "5-year JIF": 0.5,
    "JIF quartile": "",
    "JIF rank": ""
  },
  {
    "Journal name": "FILM CRITICISM",
    "ISSN": "0163-5069",
    "eISSN": "0163-5069",
    "Category": "FILM, RADIO, TELEVISION",
    "Edition": "AHCI",
    "2025 JIF": 0.2,
    "5-year JIF": 0.2,
    "JIF quartile": "",
    "JIF rank": ""
  },
  {
    "Journal name": "Acta Universitatis Sapientiae-Film and Media Studies",
    "ISSN": "2065-5924",
    "eISSN": "2066-7779",
    "Category": "FILM, RADIO, TELEVISION",
    "Edition": "ESCI",
    "2025 JIF": 0.2,
    "5-year JIF": 0.2,
    "JIF quartile": "",
    "JIF rank": ""
  },
  {
    "Journal name": "CAMERA OBSCURA",
    "ISSN": "0270-5346",
    "eISSN": "1529-1510",
    "Category": "FILM, RADIO, TELEVISION",
    "Edition": "AHCI",
    "2025 JIF": 0.2,
    "5-year JIF": 0.2,
    "JIF quartile": "",
    "JIF rank": ""
  },
  {
    "Journal name": "Short Film Studies",
    "ISSN": "2042-7824",
    "eISSN": "2042-7832",
    "Category": "FILM, RADIO, TELEVISION",
    "Edition": "ESCI",
    "2025 JIF": 0.2,
    "5-year JIF": 0.1,
    "JIF quartile": "",
    "JIF rank": ""
  },
  {
    "Journal name": "Studies in Russian and Soviet Cinema",
    "ISSN": "1750-3132",
    "eISSN": "1750-3140",
    "Category": "FILM, RADIO, TELEVISION",
    "Edition": "ESCI",
    "2025 JIF": 0.1,
    "5-year JIF": 0.2,
    "JIF quartile": "",
    "JIF rank": ""
  },
  {
    "Journal name": "JOURNAL OF FILM AND VIDEO",
    "ISSN": "0742-4671",
    "eISSN": "1934-6018",
    "Category": "FILM, RADIO, TELEVISION",
    "Edition": "AHCI",
    "2025 JIF": 0.1,
    "5-year JIF": 0.2,
    "JIF quartile": "",
    "JIF rank": ""
  },
  {
    "Journal name": "Canadian Journal of Film Studies-Revue Canadienne d Etudes Cinematographiques",
    "ISSN": "0847-5911",
    "eISSN": "2561-424X",
    "Category": "FILM, RADIO, TELEVISION",
    "Edition": "AHCI",
    "2025 JIF": 0.1,
    "5-year JIF": 0.3,
    "JIF quartile": "",
    "JIF rank": ""
  },
  {
    "Journal name": "Science Fiction Film and Television",
    "ISSN": "1754-3770",
    "eISSN": "1754-3789",
    "Category": "FILM, RADIO, TELEVISION",
    "Edition": "ESCI",
    "2025 JIF": 0.1,
    "5-year JIF": 0.6,
    "JIF quartile": "",
    "JIF rank": ""
  },
  {
    "Journal name": "Studi Pasoliniani-Rivista Internazionale",
    "ISSN": "1972-473X",
    "eISSN": "1973-3232",
    "Category": "FILM, RADIO, TELEVISION",
    "Edition": "ESCI",
    "2025 JIF": 0.1,
    "5-year JIF": "<0.1",
    "JIF quartile": "",
    "JIF rank": ""
  },
  {
    "Journal name": "Journal of Italian Cinema and Media Studies",
    "ISSN": "2047-7368",
    "eISSN": "2047-7376",
    "Category": "FILM, RADIO, TELEVISION",
    "Edition": "ESCI",
    "2025 JIF": 0.1,
    "5-year JIF": 0.2,
    "JIF quartile": "",
    "JIF rank": ""
  },
  {
    "Journal name": "Con A de Animacion",
    "ISSN": "2173-6049",
    "eISSN": "2173-3511",
    "Category": "FILM, RADIO, TELEVISION",
    "Edition": "ESCI",
    "2025 JIF": 0.1,
    "5-year JIF": 0.3,
    "JIF quartile": "",
    "JIF rank": ""
  },
  {
    "Journal name": "Black Camera",
    "ISSN": "1536-3155",
    "eISSN": "1947-4237",
    "Category": "FILM, RADIO, TELEVISION",
    "Edition": "ESCI",
    "2025 JIF": 0.1,
    "5-year JIF": 0.2,
    "JIF quartile": "",
    "JIF rank": ""
  },
  {
    "Journal name": "Music and The Moving Image",
    "ISSN": "2167-8464",
    "eISSN": "1940-7610",
    "Category": "FILM, RADIO, TELEVISION",
    "Edition": "ESCI",
    "2025 JIF": 0.1,
    "5-year JIF": "",
    "JIF quartile": "",
    "JIF rank": ""
  },
  {
    "Journal name": "CINEASTE",
    "ISSN": "0009-7004",
    "eISSN": "0009-7004",
    "Category": "FILM, RADIO, TELEVISION",
    "Edition": "AHCI",
    "2025 JIF": 0.1,
    "5-year JIF": 0.3,
    "JIF quartile": "",
    "JIF rank": ""
  },
  {
    "Journal name": "Film International",
    "ISSN": "1651-6826",
    "eISSN": "2040-3801",
    "Category": "FILM, RADIO, TELEVISION",
    "Edition": "ESCI",
    "2025 JIF": 0.1,
    "5-year JIF": "<0.1",
    "JIF quartile": "",
    "JIF rank": ""
  },
  {
    "Journal name": "SIGHT AND SOUND",
    "ISSN": "0037-4806",
    "eISSN": "0037-4806",
    "Category": "FILM, RADIO, TELEVISION",
    "Edition": "AHCI",
    "2025 JIF": 0.1,
    "5-year JIF": 0.1,
    "JIF quartile": "",
    "JIF rank": ""
  },
  {
    "Journal name": "CINEFORUM",
    "ISSN": "0009-7039",
    "eISSN": "0009-7039",
    "Category": "FILM, RADIO, TELEVISION",
    "Edition": "AHCI",
    "2025 JIF": 0.1,
    "5-year JIF": "<0.1",
    "JIF quartile": "",
    "JIF rank": ""
  },
  {
    "Journal name": "Journal of African Cinemas",
    "ISSN": "1754-9221",
    "eISSN": "1754-923X",
    "Category": "FILM, RADIO, TELEVISION",
    "Edition": "ESCI",
    "2025 JIF": "<0.1",
    "5-year JIF": 0.1,
    "JIF quartile": "",
    "JIF rank": ""
  },
  {
    "Journal name": "Music Sound and the Moving Image",
    "ISSN": "1753-0768",
    "eISSN": "1753-0776",
    "Category": "FILM, RADIO, TELEVISION",
    "Edition": "ESCI",
    "2025 JIF": "<0.1",
    "5-year JIF": 0.2,
    "JIF quartile": "",
    "JIF rank": ""
  },
  {
    "Journal name": "Cinema-Journal of Philosophy and the Moving Image",
    "ISSN": "1647-8991",
    "eISSN": "1647-8991",
    "Category": "FILM, RADIO, TELEVISION",
    "Edition": "ESCI",
    "2025 JIF": "<0.1",
    "5-year JIF": 0.2,
    "JIF quartile": "",
    "JIF rank": ""
  },
  {
    "Journal name": "Atalante-Revista de Estudios Cinematograficos",
    "ISSN": "1885-3730",
    "eISSN": "2340-6992",
    "Category": "FILM, RADIO, TELEVISION",
    "Edition": "AHCI",
    "2025 JIF": "<0.1",
    "5-year JIF": 0.1,
    "JIF quartile": "",
    "JIF rank": ""
  },
  {
    "Journal name": "Etica & Cine",
    "ISSN": "2250-5660",
    "eISSN": "2250-5415",
    "Category": "FILM, RADIO, TELEVISION",
    "Edition": "ESCI",
    "2025 JIF": "<0.1",
    "5-year JIF": "<0.1",
    "JIF quartile": "",
    "JIF rank": ""
  },
  {
    "Journal name": "Cinemas",
    "ISSN": "1181-6945",
    "eISSN": "1705-6500",
    "Category": "FILM, RADIO, TELEVISION",
    "Edition": "ESCI",
    "2025 JIF": "<0.1",
    "5-year JIF": 0.1,
    "JIF quartile": "",
    "JIF rank": ""
  },
  {
    "Journal name": "Cinemas d Amerique Latine",
    "ISSN": "1267-4397",
    "eISSN": "",
    "Category": "FILM, RADIO, TELEVISION",
    "Edition": "AHCI",
    "2025 JIF": "<0.1",
    "5-year JIF": "<0.1",
    "JIF quartile": "",
    "JIF rank": ""
  },
  {
    "Journal name": "Hrvatski Filmski Ljetopis",
    "ISSN": "1330-7665",
    "eISSN": "",
    "Category": "FILM, RADIO, TELEVISION",
    "Edition": "AHCI",
    "2025 JIF": "<0.1",
    "5-year JIF": "<0.1",
    "JIF quartile": "",
    "JIF rank": ""
  },
  {
    "Journal name": "MILLENNIUM FILM JOURNAL",
    "ISSN": "1064-5586",
    "eISSN": "1064-5586",
    "Category": "FILM, RADIO, TELEVISION",
    "Edition": "AHCI",
    "2025 JIF": "<0.1",
    "5-year JIF": 0.3,
    "JIF quartile": "",
    "JIF rank": ""
  },
  {
    "Journal name": "Eastern European Screen Studies",
    "ISSN": "2997-4828",
    "eISSN": "2997-4836",
    "Category": "FILM, RADIO, TELEVISION",
    "Edition": "ESCI",
    "2025 JIF": "",
    "5-year JIF": "",
    "JIF quartile": "",
    "JIF rank": ""
  }
]