[
  {
    "Journal name": "Nature Cities",
    "ISSN": "",
    "eISSN": "2731-9997",
    "Category": "URBAN STUDIES",
    "Edition": "ESCI",
    "2025 JIF": 15.3,
    "5-year JIF": 15.3,
    "JIF quartile": "Q1",
    "JIF rank": "1/86"
  },
  {
    "Journal name": "LANDSCAPE AND URBAN PLANNING",
    "ISSN": "0169-2046",
    "eISSN": "1872-6062",
    "Category": "URBAN STUDIES",
    "Edition": "SSCI",
    "2025 JIF": 11.4,
    "5-year JIF": 12.4,
    "JIF quartile": "Q1",
    "JIF rank": "2/86"
  },
  {
    "Journal name": "npj Urban Sustainability",
    "ISSN": "",
    "eISSN": "2661-8001",
    "Category": "URBAN STUDIES",
    "Edition": "SSCI",
    "2025 JIF": 10.9,
    "5-year JIF": 12.5,
    "JIF quartile": "Q1",
    "JIF rank": "3/86"
  },
  {
    "Journal name": "HABITAT INTERNATIONAL",
    "ISSN": "0197-3975",
    "eISSN": "1873-5428",
    "Category": "URBAN STUDIES",
    "Edition": "SSCI",
    "2025 JIF": 8.5,
    "5-year JIF": 9.1,
    "JIF quartile": "Q1",
    "JIF rank": "4/86"
  },
  {
    "Journal name": "URBAN FORESTRY & URBAN GREENING",
    "ISSN": "1618-8667",
    "eISSN": "1610-8167",
    "Category": "URBAN STUDIES",
    "Edition": "SSCI",
    "2025 JIF": 8.2,
    "5-year JIF": 8.5,
    "JIF quartile": "Q1",
    "JIF rank": "5/86"
  },
  {
    "Journal name": "CITIES",
    "ISSN": "0264-2751",
    "eISSN": "1873-6084",
    "Category": "URBAN STUDIES",
    "Edition": "SSCI",
    "2025 JIF": 7,
    "5-year JIF": 8,
    "JIF quartile": "Q1",
    "JIF rank": "6/86"
  },
  {
    "Journal name": "Smart Cities",
    "ISSN": "",
    "eISSN": "2624-6511",
    "Category": "URBAN STUDIES",
    "Edition": "ESCI",
    "2025 JIF": 6.6,
    "5-year JIF": 7.2,
    "JIF quartile": "Q1",
    "JIF rank": "7/86"
  },
  {
    "Journal name": "JOURNAL OF ARCHITECTURAL AND PLANNING RESEARCH",
    "ISSN": "0738-0895",
    "eISSN": "0738-0895",
    "Category": "URBAN STUDIES",
    "Edition": "SSCI",
    "2025 JIF": 6.3,
    "5-year JIF": 4.2,
    "JIF quartile": "Q1",
    "JIF rank": "8/86"
  },
  {
    "Journal name": "JOURNAL OF PLANNING LITERATURE",
    "ISSN": "0885-4122",
    "eISSN": "1552-6593",
    "Category": "URBAN STUDIES",
    "Edition": "SSCI",
    "2025 JIF": 6.2,
    "5-year JIF": 7.7,
    "JIF quartile": "Q1",
    "JIF rank": "9/86"
  },
  {
    "Journal name": "Journal of Urban Management",
    "ISSN": "2226-5856",
    "eISSN": "2589-0360",
    "Category": "URBAN STUDIES",
    "Edition": "ESCI",
    "2025 JIF": 5.6,
    "5-year JIF": 5.6,
    "JIF quartile": "Q1",
    "JIF rank": "10/86"
  },
  {
    "Journal name": "URBAN STUDIES",
    "ISSN": "0042-0980",
    "eISSN": "1360-063X",
    "Category": "URBAN STUDIES",
    "Edition": "SSCI",
    "2025 JIF": 4.4,
    "5-year JIF": 5.8,
    "JIF quartile": "Q1",
    "JIF rank": "11/86"
  },
  {
    "Journal name": "Planning Theory & Practice",
    "ISSN": "1464-9357",
    "eISSN": "1470-000X",
    "Category": "URBAN STUDIES",
    "Edition": "SSCI",
    "2025 JIF": 4.3,
    "5-year JIF": 4.4,
    "JIF quartile": "Q1",
    "JIF rank": "12/86"
  },
  {
    "Journal name": "JOURNAL OF URBAN TECHNOLOGY",
    "ISSN": "1063-0732",
    "eISSN": "1466-1853",
    "Category": "URBAN STUDIES",
    "Edition": "SSCI",
    "2025 JIF": 4.2,
    "5-year JIF": 5.9,
    "JIF quartile": "Q1",
    "JIF rank": "13/86"
  },
  {
    "Journal name": "JOURNAL OF THE AMERICAN PLANNING ASSOCIATION",
    "ISSN": "0194-4363",
    "eISSN": "1939-0130",
    "Category": "URBAN STUDIES",
    "Edition": "SSCI",
    "2025 JIF": 4.2,
    "5-year JIF": 5.7,
    "JIF quartile": "Q1",
    "JIF rank": "13/86"
  },
  {
    "Journal name": "EUROPEAN URBAN AND REGIONAL STUDIES",
    "ISSN": "0969-7764",
    "eISSN": "1461-7145",
    "Category": "URBAN STUDIES",
    "Edition": "SSCI",
    "2025 JIF": 4.1,
    "5-year JIF": 4.1,
    "JIF quartile": "Q1",
    "JIF rank": "15/86"
  },
  {
    "Journal name": "JOURNAL OF URBAN ECONOMICS",
    "ISSN": "0094-1190",
    "eISSN": "1095-9068",
    "Category": "URBAN STUDIES",
    "Edition": "SSCI",
    "2025 JIF": 4,
    "5-year JIF": 6.5,
    "JIF quartile": "Q1",
    "JIF rank": "16/86"
  },
  {
    "Journal name": "Buildings & Cities",
    "ISSN": "2632-6655",
    "eISSN": "2632-6655",
    "Category": "URBAN STUDIES",
    "Edition": "ESCI",
    "2025 JIF": 3.7,
    "5-year JIF": 4.5,
    "JIF quartile": "Q1",
    "JIF rank": "17/86"
  },
  {
    "Journal name": "Journal of Housing and the Built Environment",
    "ISSN": "1566-4910",
    "eISSN": "1573-7772",
    "Category": "URBAN STUDIES",
    "Edition": "SSCI",
    "2025 JIF": 3.4,
    "5-year JIF": 3.2,
    "JIF quartile": "Q1",
    "JIF rank": "18/86"
  },
  {
    "Journal name": "Frontiers in Sustainable Cities",
    "ISSN": "",
    "eISSN": "2624-9634",
    "Category": "URBAN STUDIES",
    "Edition": "ESCI",
    "2025 JIF": 3.3,
    "5-year JIF": 3.9,
    "JIF quartile": "Q1",
    "JIF rank": "19/86"
  },
  {
    "Journal name": "EUROPEAN PLANNING STUDIES",
    "ISSN": "0965-4313",
    "eISSN": "1469-5944",
    "Category": "URBAN STUDIES",
    "Edition": "SSCI",
    "2025 JIF": 3.2,
    "5-year JIF": 3.9,
    "JIF quartile": "Q1",
    "JIF rank": "20/86"
  },
  {
    "Journal name": "Urban Science",
    "ISSN": "",
    "eISSN": "2413-8851",
    "Category": "URBAN STUDIES",
    "Edition": "ESCI",
    "2025 JIF": 3.2,
    "5-year JIF": 3.2,
    "JIF quartile": "Q1",
    "JIF rank": "20/86"
  },
  {
    "Journal name": "URBAN GEOGRAPHY",
    "ISSN": "0272-3638",
    "eISSN": "1938-2847",
    "Category": "URBAN STUDIES",
    "Edition": "SSCI",
    "2025 JIF": 3.1,
    "5-year JIF": 4.3,
    "JIF quartile": "Q2",
    "JIF rank": "22/86"
  },
  {
    "Journal name": "JOURNAL OF HOUSING ECONOMICS",
    "ISSN": "1051-1377",
    "eISSN": "1096-0791",
    "Category": "URBAN STUDIES",
    "Edition": "SSCI",
    "2025 JIF": 3.1,
    "5-year JIF": 2.7,
    "JIF quartile": "Q2",
    "JIF rank": "22/86"
  },
  {
    "Journal name": "Environment and Planning B-Urban Analytics and City Science",
    "ISSN": "2399-8083",
    "eISSN": "2399-8091",
    "Category": "URBAN STUDIES",
    "Edition": "SSCI",
    "2025 JIF": 2.9,
    "5-year JIF": 3.8,
    "JIF quartile": "Q2",
    "JIF rank": "24/86"
  },
  {
    "Journal name": "Local Environment",
    "ISSN": "1354-9839",
    "eISSN": "1469-6711",
    "Category": "URBAN STUDIES",
    "Edition": "SSCI",
    "2025 JIF": 2.8,
    "5-year JIF": 3.3,
    "JIF quartile": "Q2",
    "JIF rank": "25/86"
  },
  {
    "Journal name": "City & Community",
    "ISSN": "1535-6841",
    "eISSN": "1540-6040",
    "Category": "URBAN STUDIES",
    "Edition": "SSCI",
    "2025 JIF": 2.7,
    "5-year JIF": 3.2,
    "JIF quartile": "Q2",
    "JIF rank": "26/86"
  },
  {
    "Journal name": "Journal of Urban Design",
    "ISSN": "1357-4809",
    "eISSN": "1469-9664",
    "Category": "URBAN STUDIES",
    "Edition": "ESCI",
    "2025 JIF": 2.7,
    "5-year JIF": 3,
    "JIF quartile": "Q2",
    "JIF rank": "26/86"
  },
  {
    "Journal name": "JOURNAL OF PLANNING EDUCATION AND RESEARCH",
    "ISSN": "0739-456X",
    "eISSN": "1552-6577",
    "Category": "URBAN STUDIES",
    "Edition": "SSCI",
    "2025 JIF": 2.7,
    "5-year JIF": 3.1,
    "JIF quartile": "Q2",
    "JIF rank": "26/86"
  },
  {
    "Journal name": "JOURNAL OF URBAN AFFAIRS",
    "ISSN": "0735-2166",
    "eISSN": "1467-9906",
    "Category": "URBAN STUDIES",
    "Edition": "SSCI",
    "2025 JIF": 2.7,
    "5-year JIF": 2.8,
    "JIF quartile": "Q2",
    "JIF rank": "26/86"
  },
  {
    "Journal name": "HOUSING STUDIES",
    "ISSN": "0267-3037",
    "eISSN": "1466-1810",
    "Category": "URBAN STUDIES",
    "Edition": "SSCI",
    "2025 JIF": 2.7,
    "5-year JIF": 4.2,
    "JIF quartile": "Q2",
    "JIF rank": "26/86"
  },
  {
    "Journal name": "Housing Theory & Society",
    "ISSN": "1403-6096",
    "eISSN": "1651-2278",
    "Category": "URBAN STUDIES",
    "Edition": "SSCI",
    "2025 JIF": 2.7,
    "5-year JIF": 4,
    "JIF quartile": "Q2",
    "JIF rank": "26/86"
  },
  {
    "Journal name": "REGIONAL SCIENCE AND URBAN ECONOMICS",
    "ISSN": "0166-0462",
    "eISSN": "1879-2308",
    "Category": "URBAN STUDIES",
    "Edition": "SSCI",
    "2025 JIF": 2.6,
    "5-year JIF": 4,
    "JIF quartile": "Q2",
    "JIF rank": "32/86"
  },
  {
    "Journal name": "JOURNAL OF URBAN PLANNING AND DEVELOPMENT",
    "ISSN": "0733-9488",
    "eISSN": "1943-5444",
    "Category": "URBAN STUDIES",
    "Edition": "SSCI",
    "2025 JIF": 2.6,
    "5-year JIF": 2.6,
    "JIF quartile": "Q2",
    "JIF rank": "32/86"
  },
  {
    "Journal name": "Open House International-Sustainable & Smart Architecture and Urban Studies",
    "ISSN": "0168-2601",
    "eISSN": "2633-9838",
    "Category": "URBAN STUDIES",
    "Edition": "SSCI",
    "2025 JIF": 2.5,
    "5-year JIF": 2.3,
    "JIF quartile": "Q2",
    "JIF rank": "34/86"
  },
  {
    "Journal name": "REAL ESTATE ECONOMICS",
    "ISSN": "1080-8620",
    "eISSN": "1540-6229",
    "Category": "URBAN STUDIES",
    "Edition": "SSCI",
    "2025 JIF": 2.5,
    "5-year JIF": 2.4,
    "JIF quartile": "Q2",
    "JIF rank": "34/86"
  },
  {
    "Journal name": "International Journal of Housing Policy",
    "ISSN": "1949-1247",
    "eISSN": "1949-1255",
    "Category": "URBAN STUDIES",
    "Edition": "SSCI",
    "2025 JIF": 2.5,
    "5-year JIF": 3.4,
    "JIF quartile": "Q2",
    "JIF rank": "34/86"
  },
  {
    "Journal name": "INTERNATIONAL JOURNAL OF URBAN AND REGIONAL RESEARCH",
    "ISSN": "0309-1317",
    "eISSN": "1468-2427",
    "Category": "URBAN STUDIES",
    "Edition": "SSCI",
    "2025 JIF": 2.4,
    "5-year JIF": 3.5,
    "JIF quartile": "Q2",
    "JIF rank": "37/86"
  },
  {
    "Journal name": "INTERNATIONAL REGIONAL SCIENCE REVIEW",
    "ISSN": "0160-0176",
    "eISSN": "1552-6925",
    "Category": "URBAN STUDIES",
    "Edition": "SSCI",
    "2025 JIF": 2.4,
    "5-year JIF": 2.3,
    "JIF quartile": "Q2",
    "JIF rank": "37/86"
  },
  {
    "Journal name": "TOWN PLANNING REVIEW",
    "ISSN": "0041-0020",
    "eISSN": "1478-341X",
    "Category": "URBAN STUDIES",
    "Edition": "ESCI",
    "2025 JIF": 2.3,
    "5-year JIF": 1.9,
    "JIF quartile": "Q2",
    "JIF rank": "39/86"
  },
  {
    "Journal name": "Urban Design International",
    "ISSN": "1357-5317",
    "eISSN": "1468-4519",
    "Category": "URBAN STUDIES",
    "Edition": "SSCI",
    "2025 JIF": 2.2,
    "5-year JIF": 3,
    "JIF quartile": "Q2",
    "JIF rank": "40/86"
  },
  {
    "Journal name": "HOUSING POLICY DEBATE",
    "ISSN": "1051-1482",
    "eISSN": "2152-050X",
    "Category": "URBAN STUDIES",
    "Edition": "SSCI",
    "2025 JIF": 2.2,
    "5-year JIF": 3.5,
    "JIF quartile": "Q2",
    "JIF rank": "40/86"
  },
  {
    "Journal name": "INTERNATIONAL JOURNAL OF URBAN SCIENCES",
    "ISSN": "1226-5934",
    "eISSN": "2161-6779",
    "Category": "URBAN STUDIES",
    "Edition": "SSCI",
    "2025 JIF": 2.2,
    "5-year JIF": 3.5,
    "JIF quartile": "Q2",
    "JIF rank": "40/86"
  },
  {
    "Journal name": "URBAN AFFAIRS REVIEW",
    "ISSN": "1078-0874",
    "eISSN": "1552-8332",
    "Category": "URBAN STUDIES",
    "Edition": "SSCI",
    "2025 JIF": 2.2,
    "5-year JIF": 2.8,
    "JIF quartile": "Q2",
    "JIF rank": "40/86"
  },
  {
    "Journal name": "Proceedings of the Institution of Civil Engineers-Urban Design and Planning",
    "ISSN": "1755-0793",
    "eISSN": "1755-0807",
    "Category": "URBAN STUDIES",
    "Edition": "ESCI",
    "2025 JIF": 2.2,
    "5-year JIF": 2,
    "JIF quartile": "Q2",
    "JIF rank": "40/86"
  },
  {
    "Journal name": "Urban Research & Practice",
    "ISSN": "1753-5069",
    "eISSN": "1753-5077",
    "Category": "URBAN STUDIES",
    "Edition": "SSCI",
    "2025 JIF": 2.2,
    "5-year JIF": 2.4,
    "JIF quartile": "Q2",
    "JIF rank": "40/86"
  },
  {
    "Journal name": "Urban, Planning and Transport Research",
    "ISSN": "",
    "eISSN": "2165-0020",
    "Category": "URBAN STUDIES",
    "Edition": "ESCI",
    "2025 JIF": 2.2,
    "5-year JIF": "",
    "JIF quartile": "Q2",
    "JIF rank": "40/86"
  },
  {
    "Journal name": "City",
    "ISSN": "1360-4813",
    "eISSN": "1470-3629",
    "Category": "URBAN STUDIES",
    "Edition": "ESCI",
    "2025 JIF": 2.1,
    "5-year JIF": "",
    "JIF quartile": "Q3",
    "JIF rank": "47/86"
  },
  {
    "Journal name": "JOURNAL OF REAL ESTATE FINANCE AND ECONOMICS",
    "ISSN": "0895-5638",
    "eISSN": "1573-045X",
    "Category": "URBAN STUDIES",
    "Edition": "SSCI",
    "2025 JIF": 2.1,
    "5-year JIF": 2.3,
    "JIF quartile": "Q3",
    "JIF rank": "47/86"
  },
  {
    "Journal name": "ENVIRONMENT AND URBANIZATION",
    "ISSN": "0956-2478",
    "eISSN": "1746-0301",
    "Category": "URBAN STUDIES",
    "Edition": "SSCI",
    "2025 JIF": 2.1,
    "5-year JIF": 3.2,
    "JIF quartile": "Q3",
    "JIF rank": "47/86"
  },
  {
    "Journal name": "Journal of Urban Ecology",
    "ISSN": "",
    "eISSN": "2058-5543",
    "Category": "URBAN STUDIES",
    "Edition": "ESCI",
    "2025 JIF": 2.1,
    "5-year JIF": "",
    "JIF quartile": "Q3",
    "JIF rank": "47/86"
  },
  {
    "Journal name": "Transactions in Planning and Urban Research",
    "ISSN": "",
    "eISSN": "2754-1223",
    "Category": "URBAN STUDIES",
    "Edition": "ESCI",
    "2025 JIF": 1.9,
    "5-year JIF": 2.4,
    "JIF quartile": "Q3",
    "JIF rank": "51/86"
  },
  {
    "Journal name": "Cities & Health",
    "ISSN": "2374-8834",
    "eISSN": "2374-8842",
    "Category": "URBAN STUDIES",
    "Edition": "ESCI",
    "2025 JIF": 1.9,
    "5-year JIF": "",
    "JIF quartile": "Q3",
    "JIF rank": "51/86"
  },
  {
    "Journal name": "URBAN EDUCATION",
    "ISSN": "0042-0859",
    "eISSN": "1552-8340",
    "Category": "URBAN STUDIES",
    "Edition": "SSCI",
    "2025 JIF": 1.8,
    "5-year JIF": 2.8,
    "JIF quartile": "Q3",
    "JIF rank": "53/86"
  },
  {
    "Journal name": "TeMA-Journal of Land Use Mobility and Environment",
    "ISSN": "1970-9889",
    "eISSN": "1970-9870",
    "Category": "URBAN STUDIES",
    "Edition": "ESCI",
    "2025 JIF": 1.8,
    "5-year JIF": 1.4,
    "JIF quartile": "Q3",
    "JIF rank": "53/86"
  },
  {
    "Journal name": "Journal of Contemporary Urban Affairs",
    "ISSN": "2475-6156",
    "eISSN": "2475-6164",
    "Category": "URBAN STUDIES",
    "Edition": "ESCI",
    "2025 JIF": 1.8,
    "5-year JIF": "",
    "JIF quartile": "Q3",
    "JIF rank": "53/86"
  },
  {
    "Journal name": "International Journal of Housing Markets and Analysis",
    "ISSN": "1753-8270",
    "eISSN": "1753-8289",
    "Category": "URBAN STUDIES",
    "Edition": "ESCI",
    "2025 JIF": 1.7,
    "5-year JIF": 1.7,
    "JIF quartile": "Q3",
    "JIF rank": "56/86"
  },
  {
    "Journal name": "Urban Planning",
    "ISSN": "2183-7635",
    "eISSN": "2183-7635",
    "Category": "URBAN STUDIES",
    "Edition": "ESCI",
    "2025 JIF": 1.7,
    "5-year JIF": 2.5,
    "JIF quartile": "Q3",
    "JIF rank": "56/86"
  },
  {
    "Journal name": "EDUCATION AND URBAN SOCIETY",
    "ISSN": "0013-1245",
    "eISSN": "1552-3535",
    "Category": "URBAN STUDIES",
    "Edition": "SSCI",
    "2025 JIF": 1.6,
    "5-year JIF": 1.8,
    "JIF quartile": "Q3",
    "JIF rank": "58/86"
  },
  {
    "Journal name": "Urban Forum",
    "ISSN": "1015-3802",
    "eISSN": "1874-6330",
    "Category": "URBAN STUDIES",
    "Edition": "ESCI",
    "2025 JIF": 1.5,
    "5-year JIF": 1.8,
    "JIF quartile": "Q3",
    "JIF rank": "59/86"
  },
  {
    "Journal name": "ECONOMIC DEVELOPMENT QUARTERLY",
    "ISSN": "0891-2424",
    "eISSN": "1552-3543",
    "Category": "URBAN STUDIES",
    "Edition": "SSCI",
    "2025 JIF": 1.4,
    "5-year JIF": 2.1,
    "JIF quartile": "Q3",
    "JIF rank": "60/86"
  },
  {
    "Journal name": "JOURNAL OF CONTEMPORARY ETHNOGRAPHY",
    "ISSN": "0891-2416",
    "eISSN": "1552-5414",
    "Category": "URBAN STUDIES",
    "Edition": "SSCI",
    "2025 JIF": 1.3,
    "5-year JIF": 2,
    "JIF quartile": "Q3",
    "JIF rank": "61/86"
  },
  {
    "Journal name": "Chinese Journal of Urban and Environmental Studies",
    "ISSN": "2345-7481",
    "eISSN": "2345-752X",
    "Category": "URBAN STUDIES",
    "Edition": "ESCI",
    "2025 JIF": 1.2,
    "5-year JIF": 1.4,
    "JIF quartile": "Q3",
    "JIF rank": "62/86"
  },
  {
    "Journal name": "Journal of Property Research",
    "ISSN": "0959-9916",
    "eISSN": "1466-4453",
    "Category": "URBAN STUDIES",
    "Edition": "ESCI",
    "2025 JIF": 1.1,
    "5-year JIF": 2.7,
    "JIF quartile": "Q3",
    "JIF rank": "63/86"
  },
  {
    "Journal name": "Urban Policy and Research",
    "ISSN": "0811-1146",
    "eISSN": "1476-7244",
    "Category": "URBAN STUDIES",
    "Edition": "SSCI",
    "2025 JIF": 1.1,
    "5-year JIF": 1.8,
    "JIF quartile": "Q3",
    "JIF rank": "63/86"
  },
  {
    "Journal name": "Urbani Izziv-Urban Challenge",
    "ISSN": "0353-6483",
    "eISSN": "1855-8399",
    "Category": "URBAN STUDIES",
    "Edition": "ESCI",
    "2025 JIF": 1.1,
    "5-year JIF": 1.3,
    "JIF quartile": "Q3",
    "JIF rank": "63/86"
  },
  {
    "Journal name": "ACE-Architecture City and Environment",
    "ISSN": "1886-4805",
    "eISSN": "1886-4805",
    "Category": "URBAN STUDIES",
    "Edition": "ESCI",
    "2025 JIF": 0.9,
    "5-year JIF": 0.7,
    "JIF quartile": "Q4",
    "JIF rank": "66/86"
  },
  {
    "Journal name": "Cityscape",
    "ISSN": "1936-007X",
    "eISSN": "1939-1935",
    "Category": "URBAN STUDIES",
    "Edition": "ESCI",
    "2025 JIF": 0.9,
    "5-year JIF": 0.8,
    "JIF quartile": "Q4",
    "JIF rank": "66/86"
  },
  {
    "Journal name": "EURE-REVISTA LATINOAMERICANA DE ESTUDIOS URBANO REGIONALES",
    "ISSN": "0250-7161",
    "eISSN": "0717-6236",
    "Category": "URBAN STUDIES",
    "Edition": "SSCI",
    "2025 JIF": 0.8,
    "5-year JIF": 0.8,
    "JIF quartile": "Q4",
    "JIF rank": "68/86"
  },
  {
    "Journal name": "Revista de Urbanismo",
    "ISSN": "0717-5051",
    "eISSN": "0717-5051",
    "Category": "URBAN STUDIES",
    "Edition": "ESCI",
    "2025 JIF": 0.8,
    "5-year JIF": 1,
    "JIF quartile": "Q4",
    "JIF rank": "68/86"
  },
  {
    "Journal name": "Revista INVI",
    "ISSN": "0718-1299",
    "eISSN": "0718-8358",
    "Category": "URBAN STUDIES",
    "Edition": "ESCI",
    "2025 JIF": 0.8,
    "5-year JIF": 1.6,
    "JIF quartile": "Q4",
    "JIF rank": "68/86"
  },
  {
    "Journal name": "International Journal of Built Environment and Sustainability",
    "ISSN": "1511-1369",
    "eISSN": "2289-8948",
    "Category": "URBAN STUDIES",
    "Edition": "ESCI",
    "2025 JIF": 0.7,
    "5-year JIF": 0.9,
    "JIF quartile": "Q4",
    "JIF rank": "71/86"
  },
  {
    "Journal name": "Ciudad y Territorio-Estudios Territoriales-CyTET",
    "ISSN": "1133-4762",
    "eISSN": "",
    "Category": "URBAN STUDIES",
    "Edition": "ESCI",
    "2025 JIF": 0.7,
    "5-year JIF": 0.8,
    "JIF quartile": "Q4",
    "JIF rank": "71/86"
  },
  {
    "Journal name": "Housing Care and Support",
    "ISSN": "1460-8790",
    "eISSN": "2042-8375",
    "Category": "URBAN STUDIES",
    "Edition": "ESCI",
    "2025 JIF": 0.5,
    "5-year JIF": 1.1,
    "JIF quartile": "Q4",
    "JIF rank": "73/86"
  },
  {
    "Journal name": "International Journal of Knowledge-Based Development",
    "ISSN": "2040-4468",
    "eISSN": "2040-4476",
    "Category": "URBAN STUDIES",
    "Edition": "ESCI",
    "2025 JIF": 0.5,
    "5-year JIF": 0.5,
    "JIF quartile": "Q4",
    "JIF rank": "73/86"
  },
  {
    "Journal name": "Territorios",
    "ISSN": "0123-8418",
    "eISSN": "2215-7484",
    "Category": "URBAN STUDIES",
    "Edition": "ESCI",
    "2025 JIF": 0.5,
    "5-year JIF": 0.6,
    "JIF quartile": "Q4",
    "JIF rank": "73/86"
  },
  {
    "Journal name": "JOURNAL OF URBAN HISTORY",
    "ISSN": "0096-1442",
    "eISSN": "1552-6771",
    "Category": "URBAN STUDIES",
    "Edition": "SSCI",
    "2025 JIF": 0.4,
    "5-year JIF": 0.7,
    "JIF quartile": "Q4",
    "JIF rank": "76/86"
  },
  {
    "Journal name": "Ciudades-Revista del Instituto Universitario de Urbanistica de la Universidad de Valladolid",
    "ISSN": "1133-6579",
    "eISSN": "2445-3943",
    "Category": "URBAN STUDIES",
    "Edition": "ESCI",
    "2025 JIF": 0.4,
    "5-year JIF": 0.6,
    "JIF quartile": "Q4",
    "JIF rank": "76/86"
  },
  {
    "Journal name": "Journal of Architecture and Planning -King Saud University",
    "ISSN": "1018-3604",
    "eISSN": "1018-3604",
    "Category": "URBAN STUDIES",
    "Edition": "ESCI",
    "2025 JIF": 0.3,
    "5-year JIF": 0.3,
    "JIF quartile": "Q4",
    "JIF rank": "78/86"
  },
  {
    "Journal name": "Bitacora Urbano Territorial",
    "ISSN": "0124-7913",
    "eISSN": "2027-145X",
    "Category": "URBAN STUDIES",
    "Edition": "ESCI",
    "2025 JIF": 0.3,
    "5-year JIF": 0.5,
    "JIF quartile": "Q4",
    "JIF rank": "78/86"
  },
  {
    "Journal name": "Urbe-Revista Brasileira de Gestao Urbana",
    "ISSN": "2175-3369",
    "eISSN": "2175-3369",
    "Category": "URBAN STUDIES",
    "Edition": "ESCI",
    "2025 JIF": 0.2,
    "5-year JIF": 0.4,
    "JIF quartile": "Q4",
    "JIF rank": "80/86"
  },
  {
    "Journal name": "Brussels Studies",
    "ISSN": "2031-0293",
    "eISSN": "2031-0293",
    "Category": "URBAN STUDIES",
    "Edition": "ESCI",
    "2025 JIF": 0.1,
    "5-year JIF": 0.3,
    "JIF quartile": "Q4",
    "JIF rank": "81/86"
  },
  {
    "Journal name": "Habitat y Sociedad",
    "ISSN": "2173-125X",
    "eISSN": "2173-125X",
    "Category": "URBAN STUDIES",
    "Edition": "ESCI",
    "2025 JIF": 0.1,
    "5-year JIF": 0.3,
    "JIF quartile": "Q4",
    "JIF rank": "81/86"
  },
  {
    "Journal name": "Revista de Direito da Cidade-City Law",
    "ISSN": "2317-7721",
    "eISSN": "2317-7721",
    "Category": "URBAN STUDIES",
    "Edition": "ESCI",
    "2025 JIF": 0.1,
    "5-year JIF": 0.1,
    "JIF quartile": "Q4",
    "JIF rank": "81/86"
  },
  {
    "Journal name": "TRIA-Territorio della Ricerca su Insediamenti e Ambiente",
    "ISSN": "1974-6849",
    "eISSN": "2281-4574",
    "Category": "URBAN STUDIES",
    "Edition": "ESCI",
    "2025 JIF": 0.1,
    "5-year JIF": 0.1,
    "JIF quartile": "Q4",
    "JIF rank": "81/86"
  },
  {
    "Journal name": "Nodo",
    "ISSN": "1909-3888",
    "eISSN": "2346-092X",
    "Category": "URBAN STUDIES",
    "Edition": "ESCI",
    "2025 JIF": 0.1,
    "5-year JIF": 0.2,
    "JIF quartile": "Q4",
    "JIF rank": "81/86"
  },
  {
    "Journal name": "Cuadernos de Vivienda y Urbanismo",
    "ISSN": "2027-2103",
    "eISSN": "2145-0226",
    "Category": "URBAN STUDIES",
    "Edition": "ESCI",
    "2025 JIF": "<0.1",
    "5-year JIF": 0.2,
    "JIF quartile": "Q4",
    "JIF rank": "86/86"
  }
]