[
  {
    "Journal name": "Politics & Gender",
    "ISSN": "1743-923X",
    "eISSN": "1743-9248",
    "Category": "WOMENS STUDIES",
    "Edition": "SSCI",
    "2025 JIF": 4.3,
    "5-year JIF": 4.9,
    "JIF quartile": "Q1",
    "JIF rank": "1/71"
  },
  {
    "Journal name": "GENDER & SOCIETY",
    "ISSN": "0891-2432",
    "eISSN": "1552-3977",
    "Category": "WOMENS STUDIES",
    "Edition": "SSCI",
    "2025 JIF": 4,
    "5-year JIF": 6.3,
    "JIF quartile": "Q1",
    "JIF rank": "2/71"
  },
  {
    "Journal name": "SEX ROLES",
    "ISSN": "0360-0025",
    "eISSN": "1573-2762",
    "Category": "WOMENS STUDIES",
    "Edition": "SSCI",
    "2025 JIF": 3.7,
    "5-year JIF": 4.8,
    "JIF quartile": "Q1",
    "JIF rank": "3/71"
  },
  {
    "Journal name": "PSYCHOLOGY OF WOMEN QUARTERLY",
    "ISSN": "0361-6843",
    "eISSN": "1471-6402",
    "Category": "WOMENS STUDIES",
    "Edition": "SSCI",
    "2025 JIF": 3.4,
    "5-year JIF": 4.4,
    "JIF quartile": "Q1",
    "JIF rank": "4/71"
  },
  {
    "Journal name": "GENDER WORK AND ORGANIZATION",
    "ISSN": "0968-6673",
    "eISSN": "1468-0432",
    "Category": "WOMENS STUDIES",
    "Edition": "SSCI",
    "2025 JIF": 3.3,
    "5-year JIF": 4.7,
    "JIF quartile": "Q1",
    "JIF rank": "5/71"
  },
  {
    "Journal name": "Gender in Management",
    "ISSN": "1754-2413",
    "eISSN": "1754-2421",
    "Category": "WOMENS STUDIES",
    "Edition": "SSCI",
    "2025 JIF": 2.9,
    "5-year JIF": 3.6,
    "JIF quartile": "Q1",
    "JIF rank": "6/71"
  },
  {
    "Journal name": "International Feminist Journal of Politics",
    "ISSN": "1461-6742",
    "eISSN": "1468-4470",
    "Category": "WOMENS STUDIES",
    "Edition": "SSCI",
    "2025 JIF": 2.8,
    "5-year JIF": 3.2,
    "JIF quartile": "Q1",
    "JIF rank": "7/71"
  },
  {
    "Journal name": "WOMENS HEALTH ISSUES",
    "ISSN": "1049-3867",
    "eISSN": "1878-4321",
    "Category": "WOMENS STUDIES",
    "Edition": "SSCI",
    "2025 JIF": 2.6,
    "5-year JIF": 3.5,
    "JIF quartile": "Q1",
    "JIF rank": "8/71"
  },
  {
    "Journal name": "Equality Diversity and Inclusion",
    "ISSN": "2040-7149",
    "eISSN": "2040-7157",
    "Category": "WOMENS STUDIES",
    "Edition": "ESCI",
    "2025 JIF": 2.6,
    "5-year JIF": 3.2,
    "JIF quartile": "Q1",
    "JIF rank": "8/71"
  },
  {
    "Journal name": "European Journal of Politics and Gender",
    "ISSN": "2515-1088",
    "eISSN": "2515-1096",
    "Category": "WOMENS STUDIES",
    "Edition": "ESCI",
    "2025 JIF": 2.5,
    "5-year JIF": 3.4,
    "JIF quartile": "Q1",
    "JIF rank": "10/71"
  },
  {
    "Journal name": "Frontiers in Global Womens Health",
    "ISSN": "",
    "eISSN": "2673-5059",
    "Category": "WOMENS STUDIES",
    "Edition": "ESCI",
    "2025 JIF": 2.5,
    "5-year JIF": 3.1,
    "JIF quartile": "Q1",
    "JIF rank": "10/71"
  },
  {
    "Journal name": "Feminist Legal Studies",
    "ISSN": "0966-3622",
    "eISSN": "1572-8455",
    "Category": "WOMENS STUDIES",
    "Edition": "SSCI",
    "2025 JIF": 2.4,
    "5-year JIF": 2.8,
    "JIF quartile": "Q1",
    "JIF rank": "12/71"
  },
  {
    "Journal name": "Affilia-Feminist Inquiry in Social Work",
    "ISSN": "0886-1099",
    "eISSN": "1552-3020",
    "Category": "WOMENS STUDIES",
    "Edition": "SSCI",
    "2025 JIF": 2.4,
    "5-year JIF": 3,
    "JIF quartile": "Q1",
    "JIF rank": "12/71"
  },
  {
    "Journal name": "VIOLENCE AGAINST WOMEN",
    "ISSN": "1077-8012",
    "eISSN": "1552-8448",
    "Category": "WOMENS STUDIES",
    "Edition": "SSCI",
    "2025 JIF": 2.4,
    "5-year JIF": 3.1,
    "JIF quartile": "Q1",
    "JIF rank": "12/71"
  },
  {
    "Journal name": "SOCIAL POLITICS",
    "ISSN": "1072-4745",
    "eISSN": "1468-2893",
    "Category": "WOMENS STUDIES",
    "Edition": "SSCI",
    "2025 JIF": 2.4,
    "5-year JIF": 3.1,
    "JIF quartile": "Q1",
    "JIF rank": "12/71"
  },
  {
    "Journal name": "FEMINISM & PSYCHOLOGY",
    "ISSN": "0959-3535",
    "eISSN": "1461-7161",
    "Category": "WOMENS STUDIES",
    "Edition": "SSCI",
    "2025 JIF": 2.2,
    "5-year JIF": 3,
    "JIF quartile": "Q1",
    "JIF rank": "16/71"
  },
  {
    "Journal name": "Feminist Media Studies",
    "ISSN": "1468-0777",
    "eISSN": "1471-5902",
    "Category": "WOMENS STUDIES",
    "Edition": "SSCI",
    "2025 JIF": 2.1,
    "5-year JIF": 2.7,
    "JIF quartile": "Q1",
    "JIF rank": "17/71"
  },
  {
    "Journal name": "WOMENS STUDIES INTERNATIONAL FORUM",
    "ISSN": "0277-5395",
    "eISSN": "1879-243X",
    "Category": "WOMENS STUDIES",
    "Edition": "SSCI",
    "2025 JIF": 2,
    "5-year JIF": 2.2,
    "JIF quartile": "Q2",
    "JIF rank": "18/71"
  },
  {
    "Journal name": "FEMINIST ECONOMICS",
    "ISSN": "1354-5701",
    "eISSN": "1466-4372",
    "Category": "WOMENS STUDIES",
    "Edition": "SSCI",
    "2025 JIF": 2,
    "5-year JIF": 4.2,
    "JIF quartile": "Q2",
    "JIF rank": "18/71"
  },
  {
    "Journal name": "RADICAL PHILOSOPHY",
    "ISSN": "0300-211X",
    "eISSN": "0030-211X",
    "Category": "WOMENS STUDIES",
    "Edition": "SSCI",
    "2025 JIF": 2,
    "5-year JIF": 2.2,
    "JIF quartile": "Q2",
    "JIF rank": "18/71"
  },
  {
    "Journal name": "SIGNS",
    "ISSN": "0097-9740",
    "eISSN": "1545-6943",
    "Category": "WOMENS STUDIES",
    "Edition": "SSCI",
    "2025 JIF": 1.9,
    "5-year JIF": 2.7,
    "JIF quartile": "Q2",
    "JIF rank": "21/71"
  },
  {
    "Journal name": "Women in Sport and Physical Activity Journal",
    "ISSN": "1063-6161",
    "eISSN": "1938-1581",
    "Category": "WOMENS STUDIES",
    "Edition": "ESCI",
    "2025 JIF": 1.9,
    "5-year JIF": "",
    "JIF quartile": "Q2",
    "JIF rank": "21/71"
  },
  {
    "Journal name": "JOURNAL OF GENDER STUDIES",
    "ISSN": "0958-9236",
    "eISSN": "1465-3869",
    "Category": "WOMENS STUDIES",
    "Edition": "SSCI",
    "2025 JIF": 1.9,
    "5-year JIF": 2.7,
    "JIF quartile": "Q2",
    "JIF rank": "21/71"
  },
  {
    "Journal name": "JOURNAL OF WOMEN & AGING",
    "ISSN": "0895-2841",
    "eISSN": "1540-7322",
    "Category": "WOMENS STUDIES",
    "Edition": "SSCI",
    "2025 JIF": 1.8,
    "5-year JIF": 2.1,
    "JIF quartile": "Q2",
    "JIF rank": "24/71"
  },
  {
    "Journal name": "JOURNAL OF WOMENS HEALTH",
    "ISSN": "1540-9996",
    "eISSN": "1931-843X",
    "Category": "WOMENS STUDIES",
    "Edition": "SSCI",
    "2025 JIF": 1.8,
    "5-year JIF": 3.2,
    "JIF quartile": "Q2",
    "JIF rank": "24/71"
  },
  {
    "Journal name": "ASIAN JOURNAL OF WOMENS STUDIES",
    "ISSN": "1225-9276",
    "eISSN": "2377-004X",
    "Category": "WOMENS STUDIES",
    "Edition": "SSCI",
    "2025 JIF": 1.8,
    "5-year JIF": 1.7,
    "JIF quartile": "Q2",
    "JIF rank": "24/71"
  },
  {
    "Journal name": "EUROPEAN JOURNAL OF WOMENS STUDIES",
    "ISSN": "1350-5068",
    "eISSN": "1461-7420",
    "Category": "WOMENS STUDIES",
    "Edition": "SSCI",
    "2025 JIF": 1.7,
    "5-year JIF": 2.3,
    "JIF quartile": "Q2",
    "JIF rank": "27/71"
  },
  {
    "Journal name": "Feminist Anthropology",
    "ISSN": "2643-7961",
    "eISSN": "2643-7961",
    "Category": "WOMENS STUDIES",
    "Edition": "ESCI",
    "2025 JIF": 1.6,
    "5-year JIF": 2.4,
    "JIF quartile": "Q2",
    "JIF rank": "28/71"
  },
  {
    "Journal name": "LGBTQ Family-An Interdisciplinary Journal",
    "ISSN": "2770-3371",
    "eISSN": "2770-338X",
    "Category": "WOMENS STUDIES",
    "Edition": "SSCI",
    "2025 JIF": 1.6,
    "5-year JIF": 2.1,
    "JIF quartile": "Q2",
    "JIF rank": "28/71"
  },
  {
    "Journal name": "FEMINIST REVIEW",
    "ISSN": "0141-7789",
    "eISSN": "1466-4380",
    "Category": "WOMENS STUDIES",
    "Edition": "SSCI",
    "2025 JIF": 1.6,
    "5-year JIF": 2.1,
    "JIF quartile": "Q2",
    "JIF rank": "28/71"
  },
  {
    "Journal name": "Journal of Women Politics & Policy",
    "ISSN": "1554-477X",
    "eISSN": "1554-4788",
    "Category": "WOMENS STUDIES",
    "Edition": "SSCI",
    "2025 JIF": 1.6,
    "5-year JIF": 2.1,
    "JIF quartile": "Q2",
    "JIF rank": "28/71"
  },
  {
    "Journal name": "Womens Reproductive Health",
    "ISSN": "2329-3691",
    "eISSN": "2329-3713",
    "Category": "WOMENS STUDIES",
    "Edition": "ESCI",
    "2025 JIF": 1.6,
    "5-year JIF": "",
    "JIF quartile": "Q2",
    "JIF rank": "28/71"
  },
  {
    "Journal name": "Women",
    "ISSN": "",
    "eISSN": "2673-4184",
    "Category": "WOMENS STUDIES",
    "Edition": "ESCI",
    "2025 JIF": 1.6,
    "5-year JIF": 1.7,
    "JIF quartile": "Q2",
    "JIF rank": "28/71"
  },
  {
    "Journal name": "Hypatia-A Journal of Feminist Philosophy",
    "ISSN": "0887-5367",
    "eISSN": "1527-2001",
    "Category": "WOMENS STUDIES",
    "Edition": "SSCI",
    "2025 JIF": 1.5,
    "5-year JIF": 2.2,
    "JIF quartile": "Q2",
    "JIF rank": "34/71"
  },
  {
    "Journal name": "Gender Place and Culture",
    "ISSN": "0966-369X",
    "eISSN": "1360-0524",
    "Category": "WOMENS STUDIES",
    "Edition": "SSCI",
    "2025 JIF": 1.5,
    "5-year JIF": 2.3,
    "JIF quartile": "Q2",
    "JIF rank": "34/71"
  },
  {
    "Journal name": "Gender and Language",
    "ISSN": "1747-6321",
    "eISSN": "1747-633X",
    "Category": "WOMENS STUDIES",
    "Edition": "SSCI",
    "2025 JIF": 1.3,
    "5-year JIF": 1.4,
    "JIF quartile": "Q3",
    "JIF rank": "36/71"
  },
  {
    "Journal name": "NORA-Nordic Journal of Feminist and Gender Research",
    "ISSN": "0803-8740",
    "eISSN": "1502-394X",
    "Category": "WOMENS STUDIES",
    "Edition": "ESCI",
    "2025 JIF": 1.3,
    "5-year JIF": 1.7,
    "JIF quartile": "Q3",
    "JIF rank": "36/71"
  },
  {
    "Journal name": "Sexes",
    "ISSN": "",
    "eISSN": "2411-5118",
    "Category": "WOMENS STUDIES",
    "Edition": "ESCI",
    "2025 JIF": 1.3,
    "5-year JIF": 1.5,
    "JIF quartile": "Q3",
    "JIF rank": "36/71"
  },
  {
    "Journal name": "AUSTRALIAN FEMINIST STUDIES",
    "ISSN": "0816-4649",
    "eISSN": "1465-3303",
    "Category": "WOMENS STUDIES",
    "Edition": "SSCI",
    "2025 JIF": 1.2,
    "5-year JIF": 1.7,
    "JIF quartile": "Q3",
    "JIF rank": "39/71"
  },
  {
    "Journal name": "Journal of Gender-Based Violence",
    "ISSN": "2398-6808",
    "eISSN": "2398-6816",
    "Category": "WOMENS STUDIES",
    "Edition": "ESCI",
    "2025 JIF": 1.2,
    "5-year JIF": 1.8,
    "JIF quartile": "Q3",
    "JIF rank": "39/71"
  },
  {
    "Journal name": "WOMEN & THERAPY",
    "ISSN": "0270-3149",
    "eISSN": "1541-0315",
    "Category": "WOMENS STUDIES",
    "Edition": "SSCI",
    "2025 JIF": 1.2,
    "5-year JIF": 1.8,
    "JIF quartile": "Q3",
    "JIF rank": "39/71"
  },
  {
    "Journal name": "Health Care for Women International",
    "ISSN": "0739-9332",
    "eISSN": "1096-4665",
    "Category": "WOMENS STUDIES",
    "Edition": "SSCI",
    "2025 JIF": 1.2,
    "5-year JIF": 1.6,
    "JIF quartile": "Q3",
    "JIF rank": "39/71"
  },
  {
    "Journal name": "Feminist Theory",
    "ISSN": "1464-7001",
    "eISSN": "1741-2773",
    "Category": "WOMENS STUDIES",
    "Edition": "SSCI",
    "2025 JIF": 1.1,
    "5-year JIF": 2.7,
    "JIF quartile": "Q3",
    "JIF rank": "43/71"
  },
  {
    "Journal name": "Women & Criminal Justice",
    "ISSN": "0897-4454",
    "eISSN": "1541-0323",
    "Category": "WOMENS STUDIES",
    "Edition": "SSCI",
    "2025 JIF": 1.1,
    "5-year JIF": 1.8,
    "JIF quartile": "Q3",
    "JIF rank": "43/71"
  },
  {
    "Journal name": "WOMEN & HEALTH",
    "ISSN": "0363-0242",
    "eISSN": "1541-0331",
    "Category": "WOMENS STUDIES",
    "Edition": "SSCI",
    "2025 JIF": 1.1,
    "5-year JIF": 1.7,
    "JIF quartile": "Q3",
    "JIF rank": "43/71"
  },
  {
    "Journal name": "Intersections-Gender and Sexuality in Asia and the Pacific",
    "ISSN": "1440-9151",
    "eISSN": "1440-9151",
    "Category": "WOMENS STUDIES",
    "Edition": "ESCI",
    "2025 JIF": 1.1,
    "5-year JIF": 0.8,
    "JIF quartile": "Q3",
    "JIF rank": "43/71"
  },
  {
    "Journal name": "Meridians-Feminism Race Transnationalism",
    "ISSN": "1536-6936",
    "eISSN": "1547-8424",
    "Category": "WOMENS STUDIES",
    "Edition": "ESCI",
    "2025 JIF": 0.9,
    "5-year JIF": 0.8,
    "JIF quartile": "Q3",
    "JIF rank": "47/71"
  },
  {
    "Journal name": "Journal of Middle East Womens Studies",
    "ISSN": "1552-5864",
    "eISSN": "1558-9579",
    "Category": "WOMENS STUDIES",
    "Edition": "SSCI",
    "2025 JIF": 0.9,
    "5-year JIF": 0.9,
    "JIF quartile": "Q3",
    "JIF rank": "47/71"
  },
  {
    "Journal name": "Agenda-Empowering Women for Gender Equity",
    "ISSN": "1013-0950",
    "eISSN": "2158-978X",
    "Category": "WOMENS STUDIES",
    "Edition": "ESCI",
    "2025 JIF": 0.9,
    "5-year JIF": 1,
    "JIF quartile": "Q3",
    "JIF rank": "47/71"
  },
  {
    "Journal name": "Gender and History",
    "ISSN": "0953-5233",
    "eISSN": "1468-0424",
    "Category": "WOMENS STUDIES",
    "Edition": "SSCI",
    "2025 JIF": 0.8,
    "5-year JIF": 0.8,
    "JIF quartile": "Q3",
    "JIF rank": "50/71"
  },
  {
    "Journal name": "Feminist Africa",
    "ISSN": "1726-4596",
    "eISSN": "1726-4596",
    "Category": "WOMENS STUDIES",
    "Edition": "ESCI",
    "2025 JIF": 0.7,
    "5-year JIF": 1.1,
    "JIF quartile": "Q3",
    "JIF rank": "51/71"
  },
  {
    "Journal name": "Asian Women",
    "ISSN": "1225-925X",
    "eISSN": "2586-5714",
    "Category": "WOMENS STUDIES",
    "Edition": "SSCI",
    "2025 JIF": 0.7,
    "5-year JIF": 0.5,
    "JIF quartile": "Q3",
    "JIF rank": "51/71"
  },
  {
    "Journal name": "International Journal of Feminist Approaches To Bioethics",
    "ISSN": "1937-4585",
    "eISSN": "1937-4577",
    "Category": "WOMENS STUDIES",
    "Edition": "SSCI",
    "2025 JIF": 0.7,
    "5-year JIF": 0.6,
    "JIF quartile": "Q3",
    "JIF rank": "51/71"
  },
  {
    "Journal name": "JOURNAL OF WOMENS HISTORY",
    "ISSN": "1042-7961",
    "eISSN": "1527-2036",
    "Category": "WOMENS STUDIES",
    "Edition": "SSCI",
    "2025 JIF": 0.6,
    "5-year JIF": 0.8,
    "JIF quartile": "Q4",
    "JIF rank": "54/71"
  },
  {
    "Journal name": "Indian Journal of Gender Studies",
    "ISSN": "0971-5215",
    "eISSN": "0973-0672",
    "Category": "WOMENS STUDIES",
    "Edition": "SSCI",
    "2025 JIF": 0.5,
    "5-year JIF": 0.8,
    "JIF quartile": "Q4",
    "JIF rank": "55/71"
  },
  {
    "Journal name": "Travail Genre et Societes",
    "ISSN": "1294-6303",
    "eISSN": "1294-6303",
    "Category": "WOMENS STUDIES",
    "Edition": "SSCI",
    "2025 JIF": 0.5,
    "5-year JIF": 0.7,
    "JIF quartile": "Q4",
    "JIF rank": "55/71"
  },
  {
    "Journal name": "Redescriptions-Political Thought Conceptual History and Feminist Theory",
    "ISSN": "",
    "eISSN": "2308-0914",
    "Category": "WOMENS STUDIES",
    "Edition": "ESCI",
    "2025 JIF": 0.4,
    "5-year JIF": "",
    "JIF quartile": "Q4",
    "JIF rank": "57/71"
  },
  {
    "Journal name": "FRONTIERS-A JOURNAL OF WOMEN STUDIES",
    "ISSN": "0160-9009",
    "eISSN": "1536-0334",
    "Category": "WOMENS STUDIES",
    "Edition": "SSCI",
    "2025 JIF": 0.4,
    "5-year JIF": 0.7,
    "JIF quartile": "Q4",
    "JIF rank": "57/71"
  },
  {
    "Journal name": "Feminist Media Histories",
    "ISSN": "",
    "eISSN": "2373-7492",
    "Category": "WOMENS STUDIES",
    "Edition": "ESCI",
    "2025 JIF": 0.3,
    "5-year JIF": 0.9,
    "JIF quartile": "Q4",
    "JIF rank": "59/71"
  },
  {
    "Journal name": "Journal of Feminist Scholarship",
    "ISSN": "2158-6179",
    "eISSN": "2158-6179",
    "Category": "WOMENS STUDIES",
    "Edition": "ESCI",
    "2025 JIF": 0.3,
    "5-year JIF": 0.6,
    "JIF quartile": "Q4",
    "JIF rank": "59/71"
  },
  {
    "Journal name": "Atlantis-Critical Studies in Gender Culture & Social Justice",
    "ISSN": "0702-7818",
    "eISSN": "1715-0698",
    "Category": "WOMENS STUDIES",
    "Edition": "ESCI",
    "2025 JIF": 0.3,
    "5-year JIF": 0.8,
    "JIF quartile": "Q4",
    "JIF rank": "59/71"
  },
  {
    "Journal name": "Feminismo-s",
    "ISSN": "",
    "eISSN": "1989-9998",
    "Category": "WOMENS STUDIES",
    "Edition": "ESCI",
    "2025 JIF": 0.3,
    "5-year JIF": 0.4,
    "JIF quartile": "Q4",
    "JIF rank": "59/71"
  },
  {
    "Journal name": "Differences-A Journal of Feminist Cultural Studies",
    "ISSN": "1040-7391",
    "eISSN": "1527-1986",
    "Category": "WOMENS STUDIES",
    "Edition": "SSCI",
    "2025 JIF": 0.2,
    "5-year JIF": 0.4,
    "JIF quartile": "Q4",
    "JIF rank": "63/71"
  },
  {
    "Journal name": "Palimpsest-A Journal on Women Gender and the Black International",
    "ISSN": "2165-1604",
    "eISSN": "2165-1612",
    "Category": "WOMENS STUDIES",
    "Edition": "ESCI",
    "2025 JIF": 0.1,
    "5-year JIF": 0.4,
    "JIF quartile": "Q4",
    "JIF rank": "64/71"
  },
  {
    "Journal name": "Feministische Studien",
    "ISSN": "0723-5186",
    "eISSN": "2365-9920",
    "Category": "WOMENS STUDIES",
    "Edition": "SSCI",
    "2025 JIF": 0.1,
    "5-year JIF": 0.1,
    "JIF quartile": "Q4",
    "JIF rank": "64/71"
  },
  {
    "Journal name": "Women and Music-A Journal of Gender and Culture",
    "ISSN": "1090-7505",
    "eISSN": "1553-0612",
    "Category": "WOMENS STUDIES",
    "Edition": "ESCI",
    "2025 JIF": 0.1,
    "5-year JIF": 0.2,
    "JIF quartile": "Q4",
    "JIF rank": "64/71"
  },
  {
    "Journal name": "Genre Sexualite & Societe",
    "ISSN": "2104-3736",
    "eISSN": "2104-3736",
    "Category": "WOMENS STUDIES",
    "Edition": "ESCI",
    "2025 JIF": 0.1,
    "5-year JIF": 0.2,
    "JIF quartile": "Q4",
    "JIF rank": "64/71"
  },
  {
    "Journal name": "Investigaciones Feministas",
    "ISSN": "2171-6080",
    "eISSN": "2171-6080",
    "Category": "WOMENS STUDIES",
    "Edition": "ESCI",
    "2025 JIF": 0.1,
    "5-year JIF": 0.6,
    "JIF quartile": "Q4",
    "JIF rank": "64/71"
  },
  {
    "Journal name": "Storia delle Donne",
    "ISSN": "1826-7513",
    "eISSN": "1826-7505",
    "Category": "WOMENS STUDIES",
    "Edition": "ESCI",
    "2025 JIF": 0.1,
    "5-year JIF": "<0.1",
    "JIF quartile": "Q4",
    "JIF rank": "64/71"
  },
  {
    "Journal name": "Feminist German Studies",
    "ISSN": "2578-5206",
    "eISSN": "2578-5192",
    "Category": "WOMENS STUDIES",
    "Edition": "ESCI",
    "2025 JIF": "<0.1",
    "5-year JIF": 0.2,
    "JIF quartile": "Q4",
    "JIF rank": "70/71"
  },
  {
    "Journal name": "Revista Artemis",
    "ISSN": "2316-5251",
    "eISSN": "1807-8214",
    "Category": "WOMENS STUDIES",
    "Edition": "ESCI",
    "2025 JIF": "<0.1",
    "5-year JIF": "<0.1",
    "JIF quartile": "Q4",
    "JIF rank": "70/71"
  }
]